mcipy/__init__.py
mcipy/client.py
mcipy/enums.py
mcipy/mcipy.py
mcipy/mcp_client.py
mcipy/mcp_integration.py
mcipy/models.py
mcipy/parser.py
mcipy/path_validator.py
mcipy/py.typed
mcipy/schema_config.py
mcipy/templating.py
mcipy/tool_manager.py
mcipy/executors/__init__.py
mcipy/executors/base.py
mcipy/executors/cli_executor.py
mcipy/executors/file_executor.py
mcipy/executors/http_executor.py
mcipy/executors/mcp_executor.py
mcipy/executors/text_executor.py
mci_py-1.2.dist-info/METADATA
mci_py-1.2.dist-info/WHEEL
mci_py-1.2.dist-info/entry_points.txt
mci_py-1.2.dist-info/licenses/LICENSE
mci_py-1.2.dist-info/RECORD
