Metadata-Version: 2.4
Name: mci-py
Version: 1.2
Summary: Python adapter for MCI
Project-URL: Repository, https://github.com/Model-Context-Interface/mci-py
Author-email: maestroerror <revaz.gh@gmail.com>
License-Expression: MIT
License-File: LICENSE
Classifier: Development Status :: 4 - Beta
Classifier: Intended Audience :: Developers
Classifier: Operating System :: OS Independent
Classifier: Programming Language :: Python
Classifier: Programming Language :: Python :: 3
Classifier: Programming Language :: Python :: 3.11
Classifier: Programming Language :: Python :: 3.12
Classifier: Programming Language :: Python :: 3.13
Classifier: Typing :: Typed
Requires-Python: <4.0,>=3.11
Requires-Dist: mcp[cli]>=1.3.2
Requires-Dist: pydantic>=2.0
Requires-Dist: pyyaml>=6.0
Requires-Dist: requests>=2.32.5
